_regview/__init__.py
_regview/auth.py
_regview/docker_registry.py
_regview/utils.py
regview-2.0.1.data/scripts/regview
regview-2.0.1.dist-info/LICENSE
regview-2.0.1.dist-info/METADATA
regview-2.0.1.dist-info/WHEEL
regview-2.0.1.dist-info/top_level.txt
regview-2.0.1.dist-info/RECORD
