Metadata-Version: 2.1
Name: regview
Version: 2.0.1
Summary: View instance information on all supported cloud providers
Home-page: https://github.com/ricardobranco777/regview
Author: Ricardo Branco
Author-email: rbranco@suse.de
License: MIT License
Keywords: regview,docker registry
Platform: UNKNOWN
Classifier: Development Status :: 4 - Beta
Classifier: Environment :: Console
Classifier: Intended Audience :: Developers
Classifier: Intended Audience :: System Administrators
Classifier: Topic :: System :: Monitoring
Classifier: License :: OSI Approved :: MIT License
Classifier: Natural Language :: English
Classifier: Operating System :: Unix
Classifier: Programming Language :: Python :: 3.6
Classifier: Programming Language :: Python :: 3.7
Classifier: Programming Language :: Python :: 3.8
Classifier: Programming Language :: Python :: 3.9
Classifier: Programming Language :: Python :: 3.10
Classifier: Programming Language :: Python :: 3 :: Only
Requires-Python: >=3.6
Requires-Dist: certifi (==2020.12.5)
Requires-Dist: chardet (==4.0.0)
Requires-Dist: docker-pycreds (==0.4.0)
Requires-Dist: idna (==2.10)
Requires-Dist: python-dateutil (==2.8.1)
Requires-Dist: requests (==2.25.1)
Requires-Dist: requests-toolbelt (==0.9.1)
Requires-Dist: six (==1.15.0)
Requires-Dist: urllib3 (==1.26.5)
